django_scim/__init__.py
django_scim/adapters.py
django_scim/constants.py
django_scim/exceptions.py
django_scim/filters.py
django_scim/middleware.py
django_scim/models.py
django_scim/schemas/README.rst
django_scim/schemas/__init__.py
django_scim/schemas/core/Group.json
django_scim/schemas/core/ResourceType.json
django_scim/schemas/core/Schema.json
django_scim/schemas/core/ServiceProviderConfig.json
django_scim/schemas/core/User.json
django_scim/schemas/extension/Enterprise-User.json
django_scim/settings.py
django_scim/urls.py
django_scim/utils.py
django_scim/views.py
django_scim2-0.19.0.dist-info/WHEEL
django_scim2-0.19.0.dist-info/LICENSE.txt
django_scim2-0.19.0.dist-info/METADATA
django_scim2-0.19.0.dist-info/RECORD
