Metadata-Version: 2.1
Name: django-scim2
Version: 0.19.0
Summary: A partial implementation of the SCIM 2.0 provider specification for use with Django.
Home-page: https://pypi.org/project/django-scim2/
License: MIT
Keywords: django,scim,scim2,2.0
Author: Paul Logston
Author-email: paul@15five.com
Maintainer: Devs
Maintainer-email: devs@15five.com
Requires-Python: >=3.8
Classifier: Development Status :: 5 - Production/Stable
Classifier: Environment :: Web Environment
Classifier: Framework :: Django
Classifier: Intended Audience :: Developers
Classifier: License :: OSI Approved :: MIT License
Classifier: Natural Language :: English
Classifier: Operating System :: OS Independent
Classifier: Programming Language :: Python :: 3
Classifier: Programming Language :: Python :: 3.8
Classifier: Programming Language :: Python :: 3.9
Classifier: Programming Language :: Python :: 3.10
Classifier: Programming Language :: Python :: 3.11
Classifier: Programming Language :: Python :: 3.10
Classifier: Programming Language :: Python :: 3.11
Classifier: Programming Language :: Python :: 3.8
Classifier: Programming Language :: Python :: 3.9
Classifier: Topic :: Internet
Classifier: Topic :: Software Development :: Libraries :: Python Modules
Requires-Dist: django (>=3.2)
Requires-Dist: scim2-filter-parser (>=0.5.0)
Project-URL: Documentation, https://django-scim2.readthedocs.io/en/stable/
Project-URL: Repository, https://github.com/15five/django-scim2
